snapfs_agent_scanner/__init__.py
snapfs_agent_scanner/agent.py
snapfs_agent_scanner/cli.py
snapfs_agent_scanner/config.py
snapfs_agent_scanner-0.2.0.dist-info/LICENSE
snapfs_agent_scanner-0.2.0.dist-info/METADATA
snapfs_agent_scanner-0.2.0.dist-info/WHEEL
snapfs_agent_scanner-0.2.0.dist-info/entry_points.txt
snapfs_agent_scanner-0.2.0.dist-info/top_level.txt
snapfs_agent_scanner-0.2.0.dist-info/RECORD
