Metadata-Version: 2.1
Name: snapfs-agent-scanner
Version: 0.2.0
Summary: Scanner agent for SnapFS.
Author-email: Ryan Galloway <ryan@rsg.io>
License: Apache License
Project-URL: Homepage, https://github.com/snapfsio/snapfs-agent-scanner
Project-URL: Source, https://github.com/snapfsio/snapfs-agent-scanner
Project-URL: Issues, https://github.com/snapfsio/snapfs-agent-scanner/issues
Classifier: Programming Language :: Python :: 3
Classifier: Programming Language :: Python :: 3 :: Only
Classifier: License :: OSI Approved :: Apache Software License
Classifier: Operating System :: OS Independent
Requires-Python: >=3.8
License-File: LICENSE
Requires-Dist: aiohttp>=3.9.0
Requires-Dist: pydantic>=2.7.0
Requires-Dist: snapfs>=0.2.0
